coconutools/__init__.py
coconutools-0.0.1.dist-info/WHEEL
coconutools-0.0.1.dist-info/METADATA
coconutools-0.0.1.dist-info/RECORD
